unscrambler/unscrambler.py
unscrambler-0.3.2.dist-info/LICENSE
unscrambler-0.3.2.dist-info/METADATA
unscrambler-0.3.2.dist-info/WHEEL
unscrambler-0.3.2.dist-info/entry_points.txt
unscrambler-0.3.2.dist-info/top_level.txt
unscrambler-0.3.2.dist-info/RECORD
